{"2017-09-04 18:13:13.958000": {"opponent_name": "", "agenda_points": 7, "deck_name": "deck1", "victory_type": "agenda", "personal_id": "AgInfusion: New Miracles for a New World", "date": "2017-09-04", "opponent_id": "Adam: Compulsive Hacker", "outcome": "win"}, "2017-09-04 18:12:36.613464": {"opponent_name": "", "agenda_points": 7, "deck_name": "deck1", "victory_type": "agenda", "personal_id": "AgInfusion: New Miracles for a New World", "date": "2017-09-04", "opponent_id": "Adam: Compulsive Hacker", "outcome": "win"}, "2017-09-04 18:03:02.888750": {"opponent_name": "", "agenda_points": 7, "deck_name": "deck1", "victory_type": "agenda", "personal_id": "Adam: Compulsive Hacker", "date": "2017-09-04", "opponent_id": "AgInfusion: New Miracles for a New World", "outcome": "win"}, "2017-09-04 18:04:52.015959": {"opponent_name": "", "agenda_points": 7, "deck_name": "deck1", "victory_type": "agenda", "personal_id": "AgInfusion: New Miracles for a New World", "date": "2017-09-04", "opponent_id": "Adam: Compulsive Hacker", "outcome": "win"}, "2017-09-04 18:19:00.833941": {"opponent_name": "", "agenda_points": 7, "deck_name": "deck1", "victory_type": "agenda", "personal_id": "AgInfusion: New Miracles for a New World", "date": "2017-09-04", "opponent_id": "Adam: Compulsive Hacker", "outcome": "win"}, "2017-09-04 18:16:20.254834": {"opponent_name": "", "agenda_points": 7, "deck_name": "deck1", "victory_type": "agenda", "personal_id": "AgInfusion: New Miracles for a New World", "date": "2017-09-04", "opponent_id": "Adam: Compulsive Hacker", "outcome": "win"}, "2017-09-04 18:06:26.526161": {"opponent_name": "", "agenda_points": 7, "deck_name": "deck1", "victory_type": "agenda", "personal_id": "AgInfusion: New Miracles for a New World", "date": "2017-09-04", "opponent_id": "Adam: Compulsive Hacker", "outcome": "win"}, "2017-09-04 18:12:48.778327": {"opponent_name": "", "agenda_points": 7, "deck_name": "deck1", "victory_type": "agenda", "personal_id": "AgInfusion: New Miracles for a New World", "date": "2017-09-04", "opponent_id": "Adam: Compulsive Hacker", "outcome": "win"}, "2017-09-04 18:18:44.833748": {"opponent_name": "", "agenda_points": 7, "deck_name": "deck1", "victory_type": "agenda", "personal_id": "AgInfusion: New Miracles for a New World", "date": "2017-09-04", "opponent_id": "Adam: Compulsive Hacker", "outcome": "win"}, "2017-09-04 18:04:36.641663": {"opponent_name": "", "agenda_points": 7, "deck_name": "deck1", "victory_type": "agenda", "personal_id": "AgInfusion: New Miracles for a New World", "date": "2017-09-04", "opponent_id": "Adam: Compulsive Hacker", "outcome": "win"}, "2017-09-04 18:11:57.716262": {"opponent_name": "", "agenda_points": 7, "deck_name": "deck1", "victory_type": "agenda", "personal_id": "AgInfusion: New Miracles for a New World", "date": "2017-09-04", "opponent_id": "Adam: Compulsive Hacker", "outcome": "win"}, "2017-09-04 18:13:27.812458": {"opponent_name": "", "agenda_points": 7, "deck_name": "deck1", "victory_type": "agenda", "personal_id": "AgInfusion: New Miracles for a New World", "date": "2017-09-04", "opponent_id": "Adam: Compulsive Hacker", "outcome": "win"}, "2017-09-04 18:13:00.958447": {"opponent_name": "", "agenda_points": 7, "deck_name": "deck1", "victory_type": "agenda", "personal_id": "AgInfusion: New Miracles for a New World", "date": "2017-09-04", "opponent_id": "Adam: Compulsive Hacker", "outcome": "win"}, "2017-09-04 18:11:04.312517": {"opponent_name": "", "agenda_points": 7, "deck_name": "deck1", "victory_type": "agenda", "personal_id": "Adam: Compulsive Hacker", "date": "2017-09-04", "opponent_id": "AgInfusion: New Miracles for a New World", "outcome": "win"}, "2017-09-04 18:13:55.269348": {"opponent_name": "", "agenda_points": 8, "deck_name": "deck1", "victory_type": "agenda", "personal_id": "AgInfusion: New Miracles for a New World", "date": "2017-09-04", "opponent_id": "Adam: Compulsive Hacker", "outcome": "win"}, "2017-09-04 18:13:41.330387": {"opponent_name": "", "agenda_points": 7, "deck_name": "deck1", "victory_type": "agenda", "personal_id": "AgInfusion: New Miracles for a New World", "date": "2017-09-04", "opponent_id": "Adam: Compulsive Hacker", "outcome": "win"}, "2017-09-04 18:02:21.105967": {"opponent_name": "", "agenda_points": 7, "deck_name": "deck1", "victory_type": "agenda", "personal_id": "Adam: Compulsive Hacker", "date": "2017-09-04", "opponent_id": "AgInfusion: New Miracles for a New World", "outcome": "win"}, "2017-09-04 18:01:47.187681": {"opponent_name": "", "agenda_points": 7, "deck_name": "deck1", "victory_type": "agenda", "personal_id": "Adam: Compulsive Hacker", "date": "2017-09-04", "opponent_id": "AgInfusion: New Miracles for a New World", "outcome": "win"}}